producer_consumer_hassou_karim/__init__.py
producer_consumer_hassou_karim/consumer.py
producer_consumer_hassou_karim/producer.py
producer_consumer_hassou_karim/producer_consumer.py
producer_consumer_hassou_karim-0.1.1.dist-info/METADATA
producer_consumer_hassou_karim-0.1.1.dist-info/WHEEL
producer_consumer_hassou_karim-0.1.1.dist-info/RECORD
